fiftyone_vertex_exporter/__init__.py
fiftyone_vertex_exporter/exporter.py
fiftyone_vertex_exporter-0.1.1.dist-info/LICENSE
fiftyone_vertex_exporter-0.1.1.dist-info/METADATA
fiftyone_vertex_exporter-0.1.1.dist-info/WHEEL
fiftyone_vertex_exporter-0.1.1.dist-info/RECORD
