Metadata-Version: 2.1
Name: fiftyone-vertex-exporter
Version: 0.1.1
Summary: 
Home-page: https://codeberg.org/anriha/fiftyone_vertex_exporter
License: MIT
Author: Antonín Říha
Author-email: antonin.riha@protonmail.com
Requires-Python: >=3.11,<4.0
Classifier: License :: OSI Approved :: MIT License
Classifier: Programming Language :: Python :: 3
Classifier: Programming Language :: Python :: 3.11
Classifier: Programming Language :: Python :: 3.12
Requires-Dist: fiftyone (>=0.25.2,<0.26.0)
Requires-Dist: jsonlines (>=4.0.0,<5.0.0)
